<annotation>
  <folder>./JPEGImages</folder>
  <filename>0_110_60_0_03661.jpg</filename>
  <source>
    <database>The pegasus Database</database>
    <annotation>Pegasus 2021</annotation>
  </source>
  <size>
    <width>640</width>
    <height>512</height>
    <depth>1</depth>
  </size>
  <segmented>0</segmented>
  <object>
    <name>Person</name>
    <pose>60</pose>
    <truncated>0</truncated>
    <difficult>0</difficult>
    <bndbox>
      <xmin>349</xmin>
      <ymin>31</ymin>
      <xmax>357</xmax>
      <ymax>50</ymax>
    </bndbox>
  </object>
  <object>
    <name>Person</name>
    <pose>60</pose>
    <truncated>0</truncated>
    <difficult>0</difficult>
    <bndbox>
      <xmin>322</xmin>
      <ymin>32</ymin>
      <xmax>336</xmax>
      <ymax>57</ymax>
    </bndbox>
  </object>
  <object>
    <name>Person</name>
    <pose>60</pose>
    <truncated>0</truncated>
    <difficult>0</difficult>
    <bndbox>
      <xmin>308</xmin>
      <ymin>28</ymin>
      <xmax>318</xmax>
      <ymax>42</ymax>
    </bndbox>
  </object>
  <object>
    <name>Person</name>
    <pose>60</pose>
    <truncated>0</truncated>
    <difficult>0</difficult>
    <bndbox>
      <xmin>246</xmin>
      <ymin>448</ymin>
      <xmax>258</xmax>
      <ymax>470</ymax>
    </bndbox>
  </object>
</annotation>
