<annotation>
  <folder>./JPEGImages</folder>
  <filename>0_120_40_0_09481.jpg</filename>
  <source>
    <database>The pegasus Database</database>
    <annotation>Pegasus 2021</annotation>
  </source>
  <size>
    <width>640</width>
    <height>512</height>
    <depth>1</depth>
  </size>
  <segmented>0</segmented>
  <object>
    <name>Car</name>
    <pose>40</pose>
    <truncated>0</truncated>
    <difficult>0</difficult>
    <bndbox>
      <xmin>222</xmin>
      <ymin>355</ymin>
      <xmax>279</xmax>
      <ymax>388</ymax>
    </bndbox>
  </object>
  <object>
    <name>Car</name>
    <pose>40</pose>
    <truncated>0</truncated>
    <difficult>0</difficult>
    <bndbox>
      <xmin>410</xmin>
      <ymin>241</ymin>
      <xmax>465</xmax>
      <ymax>273</ymax>
    </bndbox>
  </object>
  <object>
    <name>Car</name>
    <pose>40</pose>
    <truncated>0</truncated>
    <difficult>0</difficult>
    <bndbox>
      <xmin>390</xmin>
      <ymin>287</ymin>
      <xmax>443</xmax>
      <ymax>316</ymax>
    </bndbox>
  </object>
  <object>
    <name>Car</name>
    <pose>40</pose>
    <truncated>0</truncated>
    <difficult>0</difficult>
    <bndbox>
      <xmin>367</xmin>
      <ymin>358</ymin>
      <xmax>420</xmax>
      <ymax>387</ymax>
    </bndbox>
  </object>
  <object>
    <name>Car</name>
    <pose>40</pose>
    <truncated>0</truncated>
    <difficult>0</difficult>
    <bndbox>
      <xmin>415</xmin>
      <ymin>405</ymin>
      <xmax>468</xmax>
      <ymax>434</ymax>
    </bndbox>
  </object>
  <object>
    <name>Car</name>
    <pose>40</pose>
    <truncated>0</truncated>
    <difficult>0</difficult>
    <bndbox>
      <xmin>561</xmin>
      <ymin>383</ymin>
      <xmax>624</xmax>
      <ymax>417</ymax>
    </bndbox>
  </object>
  <object>
    <name>Car</name>
    <pose>40</pose>
    <truncated>0</truncated>
    <difficult>0</difficult>
    <bndbox>
      <xmin>444</xmin>
      <ymin>318</ymin>
      <xmax>501</xmax>
      <ymax>346</ymax>
    </bndbox>
  </object>
  <object>
    <name>Car</name>
    <pose>40</pose>
    <truncated>0</truncated>
    <difficult>0</difficult>
    <bndbox>
      <xmin>572</xmin>
      <ymin>348</ymin>
      <xmax>629</xmax>
      <ymax>376</ymax>
    </bndbox>
  </object>
  <object>
    <name>Car</name>
    <pose>40</pose>
    <truncated>0</truncated>
    <difficult>0</difficult>
    <bndbox>
      <xmin>334</xmin>
      <ymin>120</ymin>
      <xmax>399</xmax>
      <ymax>158</ymax>
    </bndbox>
  </object>
  <object>
    <name>Car</name>
    <pose>40</pose>
    <truncated>0</truncated>
    <difficult>0</difficult>
    <bndbox>
      <xmin>135</xmin>
      <ymin>177</ymin>
      <xmax>189</xmax>
      <ymax>209</ymax>
    </bndbox>
  </object>
</annotation>
