<annotation verified="no">
  <folder>20210121</folder>
  <filename>0_100_50_0_08162</filename>
  <path>C:\Users\94795\Desktop\day\100m\-50\20210121\0_100_50_0_08162.jpg</path>
  <source>
    <database>Unknown</database>
  </source>
  <size>
    <width>640</width>
    <height>512</height>
    <depth>1</depth>
  </size>
  <segmented>0</segmented>
  <object>
    <type>robndbox</type>
    <name>Car</name>
    <pose>Unspecified</pose>
    <truncated>0</truncated>
    <difficult>0</difficult>
    <robndbox>
      <cx>604.5423</cx>
      <cy>241.2623</cy>
      <w>28.6929</w>
      <h>57.7178</h>
      <angle>3.116722</angle>
    </robndbox>
  </object>
  <object>
    <type>robndbox</type>
    <name>Car</name>
    <pose>Unspecified</pose>
    <truncated>0</truncated>
    <difficult>0</difficult>
    <robndbox>
      <cx>525.6667</cx>
      <cy>223.0556</cy>
      <w>34.3794</w>
      <h>65.9019</h>
      <angle>0.103433</angle>
    </robndbox>
  </object>
  <object>
    <type>robndbox</type>
    <name>Car</name>
    <pose>Unspecified</pose>
    <truncated>0</truncated>
    <difficult>0</difficult>
    <robndbox>
      <cx>454.1667</cx>
      <cy>216.5556</cy>
      <w>30.0</w>
      <h>65.0</h>
      <angle>0.0</angle>
    </robndbox>
  </object>
  <object>
    <type>robndbox</type>
    <name>Car</name>
    <pose>Unspecified</pose>
    <truncated>0</truncated>
    <difficult>0</difficult>
    <robndbox>
      <cx>340.7654</cx>
      <cy>201.4993</cy>
      <w>34.0324</w>
      <h>64.0842</h>
      <angle>0.220006</angle>
    </robndbox>
  </object>
  <object>
    <type>robndbox</type>
    <name>Car</name>
    <pose>Unspecified</pose>
    <truncated>0</truncated>
    <difficult>0</difficult>
    <robndbox>
      <cx>277.8835</cx>
      <cy>140.6862</cy>
      <w>34.0124</w>
      <h>65.3754</h>
      <angle>0.110928</angle>
    </robndbox>
  </object>
  <object>
    <type>robndbox</type>
    <name>Car</name>
    <pose>Unspecified</pose>
    <truncated>0</truncated>
    <difficult>0</difficult>
    <robndbox>
      <cx>106.4841</cx>
      <cy>167.8035</cy>
      <w>32.4863</w>
      <h>58.127</h>
      <angle>0.459082</angle>
    </robndbox>
  </object>
  <object>
    <type>robndbox</type>
    <name>Car</name>
    <pose>Unspecified</pose>
    <truncated>0</truncated>
    <difficult>0</difficult>
    <robndbox>
      <cx>358.1667</cx>
      <cy>28.5556</cy>
      <w>30.0</w>
      <h>53.0</h>
      <angle>0.0</angle>
    </robndbox>
  </object>
  <object>
    <type>robndbox</type>
    <name>Car</name>
    <pose>Unspecified</pose>
    <truncated>0</truncated>
    <difficult>0</difficult>
    <robndbox>
      <cx>429.1667</cx>
      <cy>29.0556</cy>
      <w>26.0</w>
      <h>58.0</h>
      <angle>0.0</angle>
    </robndbox>
  </object>
  <object>
    <type>robndbox</type>
    <name>Car</name>
    <pose>Unspecified</pose>
    <truncated>0</truncated>
    <difficult>0</difficult>
    <robndbox>
      <cx>608.6667</cx>
      <cy>38.0556</cy>
      <w>29.0</w>
      <h>60.0</h>
      <angle>0.0</angle>
    </robndbox>
  </object>
  <object>
    <type>robndbox</type>
    <name>Car</name>
    <pose>Unspecified</pose>
    <truncated>0</truncated>
    <difficult>0</difficult>
    <robndbox>
      <cx>569.6667</cx>
      <cy>39.5556</cy>
      <w>29.0</w>
      <h>47.0</h>
      <angle>0.0</angle>
    </robndbox>
  </object>
  <object>
    <type>robndbox</type>
    <name>Car</name>
    <pose>Unspecified</pose>
    <truncated>0</truncated>
    <difficult>0</difficult>
    <robndbox>
      <cx>501.6667</cx>
      <cy>37.0556</cy>
      <w>27.0</w>
      <h>42.0</h>
      <angle>0.0</angle>
    </robndbox>
  </object>
  <object>
    <type>robndbox</type>
    <name>Car</name>
    <pose>Unspecified</pose>
    <truncated>0</truncated>
    <difficult>0</difficult>
    <robndbox>
      <cx>467.1667</cx>
      <cy>33.5556</cy>
      <w>28.4102</w>
      <h>50.5753</h>
      <angle>0.11445</angle>
    </robndbox>
  </object>
  <object>
    <type>robndbox</type>
    <name>Car</name>
    <pose>Unspecified</pose>
    <truncated>0</truncated>
    <difficult>0</difficult>
    <robndbox>
      <cx>183.1667</cx>
      <cy>18.5556</cy>
      <w>32.0</w>
      <h>35.0</h>
      <angle>0.0</angle>
    </robndbox>
  </object>
  <object>
    <type>robndbox</type>
    <name>Car</name>
    <pose>Unspecified</pose>
    <truncated>0</truncated>
    <difficult>0</difficult>
    <robndbox>
      <cx>256.6667</cx>
      <cy>21.0556</cy>
      <w>33.0</w>
      <h>42.0</h>
      <angle>0.0</angle>
    </robndbox>
  </object>
  <object>
    <type>robndbox</type>
    <name>Car</name>
    <pose>Unspecified</pose>
    <truncated>0</truncated>
    <difficult>0</difficult>
    <robndbox>
      <cx>155.1667</cx>
      <cy>177.5556</cy>
      <w>32.4922</w>
      <h>57.2823</h>
      <angle>0.215711</angle>
    </robndbox>
  </object>
  <object>
    <type>robndbox</type>
    <name>OtherVehicle</name>
    <pose>Unspecified</pose>
    <truncated>0</truncated>
    <difficult>0</difficult>
    <robndbox>
      <cx>61.1667</cx>
      <cy>281.0556</cy>
      <w>37.938</w>
      <h>71.1387</h>
      <angle>0.313012</angle>
    </robndbox>
  </object>
</annotation>
