<annotation verified="no">
  <folder>20210121</folder>
  <filename>0_110_40_0_08350</filename>
  <path>C:\Users\94795\Desktop\day\110m\-40\20210121\0_110_40_0_08350.jpg</path>
  <source>
    <database>Unknown</database>
  </source>
  <size>
    <width>640</width>
    <height>512</height>
    <depth>1</depth>
  </size>
  <segmented>0</segmented>
  <object>
    <type>robndbox</type>
    <name>Car</name>
    <pose>Unspecified</pose>
    <truncated>0</truncated>
    <difficult>0</difficult>
    <robndbox>
      <cx>274.193</cx>
      <cy>399.3697</cy>
      <w>22.2888</w>
      <h>42.1475</h>
      <angle>0.139877</angle>
    </robndbox>
  </object>
  <object>
    <type>robndbox</type>
    <name>Car</name>
    <pose>Unspecified</pose>
    <truncated>0</truncated>
    <difficult>0</difficult>
    <robndbox>
      <cx>310.0957</cx>
      <cy>407.9527</cy>
      <w>23.5148</w>
      <h>46.2282</h>
      <angle>3.069879</angle>
    </robndbox>
  </object>
  <object>
    <type>robndbox</type>
    <name>Car</name>
    <pose>Unspecified</pose>
    <truncated>0</truncated>
    <difficult>0</difficult>
    <robndbox>
      <cx>366.4309</cx>
      <cy>410.8584</cy>
      <w>24.8122</w>
      <h>40.8303</h>
      <angle>0.118664</angle>
    </robndbox>
  </object>
  <object>
    <type>robndbox</type>
    <name>Car</name>
    <pose>Unspecified</pose>
    <truncated>0</truncated>
    <difficult>0</difficult>
    <robndbox>
      <cx>572.7895</cx>
      <cy>178.3774</cy>
      <w>20.9952</w>
      <h>37.7995</h>
      <angle>3.000821</angle>
    </robndbox>
  </object>
  <object>
    <type>robndbox</type>
    <name>Car</name>
    <pose>Unspecified</pose>
    <truncated>0</truncated>
    <difficult>0</difficult>
    <robndbox>
      <cx>516.6667</cx>
      <cy>169.0556</cy>
      <w>23.0</w>
      <h>42.0</h>
      <angle>0.0</angle>
    </robndbox>
  </object>
  <object>
    <type>robndbox</type>
    <name>Car</name>
    <pose>Unspecified</pose>
    <truncated>0</truncated>
    <difficult>0</difficult>
    <robndbox>
      <cx>462.6667</cx>
      <cy>168.5556</cy>
      <w>21.0</w>
      <h>43.0</h>
      <angle>0.0</angle>
    </robndbox>
  </object>
  <object>
    <type>robndbox</type>
    <name>Car</name>
    <pose>Unspecified</pose>
    <truncated>0</truncated>
    <difficult>0</difficult>
    <robndbox>
      <cx>380.7239</cx>
      <cy>161.91</cy>
      <w>21.2725</w>
      <h>39.4664</h>
      <angle>0.155924</angle>
    </robndbox>
  </object>
  <object>
    <type>robndbox</type>
    <name>Car</name>
    <pose>Unspecified</pose>
    <truncated>0</truncated>
    <difficult>0</difficult>
    <robndbox>
      <cx>332.6667</cx>
      <cy>127.5556</cy>
      <w>21.0</w>
      <h>39.0</h>
      <angle>0.0</angle>
    </robndbox>
  </object>
  <object>
    <type>robndbox</type>
    <name>Car</name>
    <pose>Unspecified</pose>
    <truncated>0</truncated>
    <difficult>0</difficult>
    <robndbox>
      <cx>626.6667</cx>
      <cy>139.5556</cy>
      <w>21.0</w>
      <h>33.0</h>
      <angle>0.0</angle>
    </robndbox>
  </object>
  <object>
    <type>robndbox</type>
    <name>Car</name>
    <pose>Unspecified</pose>
    <truncated>0</truncated>
    <difficult>0</difficult>
    <robndbox>
      <cx>403.1667</cx>
      <cy>30.5556</cy>
      <w>18.0</w>
      <h>31.0</h>
      <angle>0.0</angle>
    </robndbox>
  </object>
  <object>
    <type>robndbox</type>
    <name>Car</name>
    <pose>Unspecified</pose>
    <truncated>0</truncated>
    <difficult>0</difficult>
    <robndbox>
      <cx>476.1667</cx>
      <cy>27.0556</cy>
      <w>18.0</w>
      <h>32.0</h>
      <angle>0.0</angle>
    </robndbox>
  </object>
  <object>
    <type>robndbox</type>
    <name>Car</name>
    <pose>Unspecified</pose>
    <truncated>0</truncated>
    <difficult>0</difficult>
    <robndbox>
      <cx>187.9286</cx>
      <cy>209.4506</cy>
      <w>23.8177</w>
      <h>45.0037</h>
      <angle>0.154907</angle>
    </robndbox>
  </object>
  <object>
    <type>robndbox</type>
    <name>Car</name>
    <pose>Unspecified</pose>
    <truncated>0</truncated>
    <difficult>0</difficult>
    <robndbox>
      <cx>252.5844</cx>
      <cy>56.3721</cy>
      <w>23.0513</w>
      <h>30.2634</h>
      <angle>0.144338</angle>
    </robndbox>
  </object>
  <object>
    <type>robndbox</type>
    <name>Car</name>
    <pose>Unspecified</pose>
    <truncated>0</truncated>
    <difficult>0</difficult>
    <robndbox>
      <cx>305.6667</cx>
      <cy>54.5556</cy>
      <w>19.0</w>
      <h>39.0</h>
      <angle>0.0</angle>
    </robndbox>
  </object>
  <object>
    <type>robndbox</type>
    <name>Car</name>
    <pose>Unspecified</pose>
    <truncated>0</truncated>
    <difficult>0</difficult>
    <robndbox>
      <cx>544.1667</cx>
      <cy>31.5556</cy>
      <w>18.0</w>
      <h>27.0</h>
      <angle>0.0</angle>
    </robndbox>
  </object>
  <object>
    <type>robndbox</type>
    <name>Car</name>
    <pose>Unspecified</pose>
    <truncated>0</truncated>
    <difficult>0</difficult>
    <robndbox>
      <cx>435.6667</cx>
      <cy>29.0556</cy>
      <w>17.0</w>
      <h>28.0</h>
      <angle>0.0</angle>
    </robndbox>
  </object>
  <object>
    <type>robndbox</type>
    <name>Car</name>
    <pose>Unspecified</pose>
    <truncated>0</truncated>
    <difficult>0</difficult>
    <robndbox>
      <cx>617.1667</cx>
      <cy>35.5556</cy>
      <w>18.0</w>
      <h>29.0</h>
      <angle>0.0</angle>
    </robndbox>
  </object>
  <object>
    <type>robndbox</type>
    <name>Car</name>
    <pose>Unspecified</pose>
    <truncated>0</truncated>
    <difficult>0</difficult>
    <robndbox>
      <cx>564.2402</cx>
      <cy>59.681</cy>
      <w>20.0117</w>
      <h>35.2278</h>
      <angle>3.028698</angle>
    </robndbox>
  </object>
  <object>
    <type>robndbox</type>
    <name>Car</name>
    <pose>Unspecified</pose>
    <truncated>0</truncated>
    <difficult>0</difficult>
    <robndbox>
      <cx>584.1667</cx>
      <cy>32.0556</cy>
      <w>16.0</w>
      <h>28.0</h>
      <angle>0.0</angle>
    </robndbox>
  </object>
  <object>
    <type>robndbox</type>
    <name>Car</name>
    <pose>Unspecified</pose>
    <truncated>0</truncated>
    <difficult>0</difficult>
    <robndbox>
      <cx>341.572</cx>
      <cy>27.7929</cy>
      <w>19.7616</w>
      <h>34.268</h>
      <angle>0.128992</angle>
    </robndbox>
  </object>
  <object>
    <type>robndbox</type>
    <name>Car</name>
    <pose>Unspecified</pose>
    <truncated>0</truncated>
    <difficult>0</difficult>
    <robndbox>
      <cx>369.6667</cx>
      <cy>26.5556</cy>
      <w>19.0</w>
      <h>35.0</h>
      <angle>0.0</angle>
    </robndbox>
  </object>
  <object>
    <type>robndbox</type>
    <name>Car</name>
    <pose>Unspecified</pose>
    <truncated>0</truncated>
    <difficult>0</difficult>
    <robndbox>
      <cx>460.6667</cx>
      <cy>61.0556</cy>
      <w>19.0</w>
      <h>38.0</h>
      <angle>0.0</angle>
    </robndbox>
  </object>
  <object>
    <type>robndbox</type>
    <name>Car</name>
    <pose>Unspecified</pose>
    <truncated>0</truncated>
    <difficult>0</difficult>
    <robndbox>
      <cx>536.6667</cx>
      <cy>62.5556</cy>
      <w>21.0</w>
      <h>29.0</h>
      <angle>0.0</angle>
    </robndbox>
  </object>
  <object>
    <type>robndbox</type>
    <name>Car</name>
    <pose>Unspecified</pose>
    <truncated>0</truncated>
    <difficult>0</difficult>
    <robndbox>
      <cx>486.6667</cx>
      <cy>62.5556</cy>
      <w>17.0</w>
      <h>27.0</h>
      <angle>0.0</angle>
    </robndbox>
  </object>
  <object>
    <type>robndbox</type>
    <name>Car</name>
    <pose>Unspecified</pose>
    <truncated>0</truncated>
    <difficult>0</difficult>
    <robndbox>
      <cx>616.7407</cx>
      <cy>67.8021</cy>
      <w>22.7107</w>
      <h>33.7443</h>
      <angle>2.872977</angle>
    </robndbox>
  </object>
  <object>
    <type>robndbox</type>
    <name>Car</name>
    <pose>Unspecified</pose>
    <truncated>0</truncated>
    <difficult>0</difficult>
    <robndbox>
      <cx>432.6667</cx>
      <cy>60.5556</cy>
      <w>19.0</w>
      <h>37.0</h>
      <angle>0.0</angle>
    </robndbox>
  </object>
  <object>
    <type>robndbox</type>
    <name>Car</name>
    <pose>Unspecified</pose>
    <truncated>0</truncated>
    <difficult>0</difficult>
    <robndbox>
      <cx>382.6667</cx>
      <cy>63.0556</cy>
      <w>21.0</w>
      <h>36.0</h>
      <angle>0.0</angle>
    </robndbox>
  </object>
  <object>
    <type>robndbox</type>
    <name>Car</name>
    <pose>Unspecified</pose>
    <truncated>0</truncated>
    <difficult>0</difficult>
    <robndbox>
      <cx>210.2803</cx>
      <cy>147.3605</cy>
      <w>21.7716</w>
      <h>36.0494</h>
      <angle>0.357681</angle>
    </robndbox>
  </object>
  <object>
    <type>robndbox</type>
    <name>Car</name>
    <pose>Unspecified</pose>
    <truncated>0</truncated>
    <difficult>0</difficult>
    <robndbox>
      <cx>246.3029</cx>
      <cy>152.2337</cy>
      <w>21.5332</w>
      <h>38.6916</h>
      <angle>0.127338</angle>
    </robndbox>
  </object>
</annotation>
