<annotation verified="no">
  <folder>20210123</folder>
  <filename>0_120_80_0_09612</filename>
  <path>C:\Users\94795\Desktop\day\120m\-80\20210123\0_120_80_0_09612.jpg</path>
  <source>
    <database>Unknown</database>
  </source>
  <size>
    <width>640</width>
    <height>512</height>
    <depth>1</depth>
  </size>
  <segmented>0</segmented>
  <object>
    <type>robndbox</type>
    <name>Car</name>
    <pose>Unspecified</pose>
    <truncated>0</truncated>
    <difficult>0</difficult>
    <robndbox>
      <cx>275.3192</cx>
      <cy>166.6817</cy>
      <w>78.3594</w>
      <h>36.9886</h>
      <angle>0.303985</angle>
    </robndbox>
  </object>
  <object>
    <type>robndbox</type>
    <name>Car</name>
    <pose>Unspecified</pose>
    <truncated>0</truncated>
    <difficult>0</difficult>
    <robndbox>
      <cx>25.6667</cx>
      <cy>438.5556</cy>
      <w>49.0</w>
      <h>75.0</h>
      <angle>0.0</angle>
    </robndbox>
  </object>
  <object>
    <type>robndbox</type>
    <name>Car</name>
    <pose>Unspecified</pose>
    <truncated>0</truncated>
    <difficult>0</difficult>
    <robndbox>
      <cx>444.9451</cx>
      <cy>138.6945</cy>
      <w>46.5292</w>
      <h>23.2685</h>
      <angle>0.216545</angle>
    </robndbox>
  </object>
  <object>
    <type>robndbox</type>
    <name>Car</name>
    <pose>Unspecified</pose>
    <truncated>0</truncated>
    <difficult>0</difficult>
    <robndbox>
      <cx>563.083</cx>
      <cy>298.5308</cy>
      <w>86.805</w>
      <h>34.1368</h>
      <angle>0.678333</angle>
    </robndbox>
  </object>
  <object>
    <type>robndbox</type>
    <name>Car</name>
    <pose>Unspecified</pose>
    <truncated>0</truncated>
    <difficult>0</difficult>
    <robndbox>
      <cx>474.2179</cx>
      <cy>167.7978</cy>
      <w>21.6432</w>
      <h>45.8281</h>
      <angle>0.522252</angle>
    </robndbox>
  </object>
</annotation>
