<annotation verified="no">
  <folder>20210115</folder>
  <filename>0_60_80_0_01795</filename>
  <path>C:\Users\94795\Desktop\day\60m\-80\20210115\0_60_80_0_01795.jpg</path>
  <source>
    <database>Unknown</database>
  </source>
  <size>
    <width>640</width>
    <height>512</height>
    <depth>1</depth>
  </size>
  <segmented>0</segmented>
  <object>
    <type>robndbox</type>
    <name>Person</name>
    <pose>Unspecified</pose>
    <truncated>0</truncated>
    <difficult>0</difficult>
    <robndbox>
      <cx>413.6667</cx>
      <cy>89.0556</cy>
      <w>13.0</w>
      <h>28.0</h>
      <angle>0.0</angle>
    </robndbox>
  </object>
  <object>
    <type>robndbox</type>
    <name>Person</name>
    <pose>Unspecified</pose>
    <truncated>0</truncated>
    <difficult>0</difficult>
    <robndbox>
      <cx>512.6667</cx>
      <cy>37.5556</cy>
      <w>13.0</w>
      <h>33.0</h>
      <angle>0.253919</angle>
    </robndbox>
  </object>
  <object>
    <type>robndbox</type>
    <name>Person</name>
    <pose>Unspecified</pose>
    <truncated>0</truncated>
    <difficult>0</difficult>
    <robndbox>
      <cx>240.1667</cx>
      <cy>410.5556</cy>
      <w>16.0</w>
      <h>21.0</h>
      <angle>0.0</angle>
    </robndbox>
  </object>
  <object>
    <type>robndbox</type>
    <name>Person</name>
    <pose>Unspecified</pose>
    <truncated>0</truncated>
    <difficult>0</difficult>
    <robndbox>
      <cx>258.6667</cx>
      <cy>322.0556</cy>
      <w>17.0</w>
      <h>22.0</h>
      <angle>0.0</angle>
    </robndbox>
  </object>
  <object>
    <type>robndbox</type>
    <name>Person</name>
    <pose>Unspecified</pose>
    <truncated>0</truncated>
    <difficult>0</difficult>
    <robndbox>
      <cx>289.1667</cx>
      <cy>342.5556</cy>
      <w>14.0</w>
      <h>23.0</h>
      <angle>0.0</angle>
    </robndbox>
  </object>
  <object>
    <type>robndbox</type>
    <name>Person</name>
    <pose>Unspecified</pose>
    <truncated>0</truncated>
    <difficult>0</difficult>
    <robndbox>
      <cx>295.1667</cx>
      <cy>371.5556</cy>
      <w>18.0</w>
      <h>21.0</h>
      <angle>0.0</angle>
    </robndbox>
  </object>
  <object>
    <type>robndbox</type>
    <name>Person</name>
    <pose>Unspecified</pose>
    <truncated>0</truncated>
    <difficult>0</difficult>
    <robndbox>
      <cx>276.6667</cx>
      <cy>435.0556</cy>
      <w>11.0</w>
      <h>20.0</h>
      <angle>0.0</angle>
    </robndbox>
  </object>
  <object>
    <type>robndbox</type>
    <name>Person</name>
    <pose>Unspecified</pose>
    <truncated>0</truncated>
    <difficult>0</difficult>
    <robndbox>
      <cx>487.1667</cx>
      <cy>68.5556</cy>
      <w>14.0</w>
      <h>27.0</h>
      <angle>0.478352</angle>
    </robndbox>
  </object>
  <object>
    <type>robndbox</type>
    <name>Person</name>
    <pose>Unspecified</pose>
    <truncated>0</truncated>
    <difficult>0</difficult>
    <robndbox>
      <cx>507.6667</cx>
      <cy>8.5556</cy>
      <w>19.0</w>
      <h>15.0</h>
      <angle>0.0</angle>
    </robndbox>
  </object>
  <object>
    <type>robndbox</type>
    <name>Person</name>
    <pose>Unspecified</pose>
    <truncated>0</truncated>
    <difficult>0</difficult>
    <robndbox>
      <cx>302.6667</cx>
      <cy>434.0556</cy>
      <w>19.0</w>
      <h>16.0</h>
      <angle>0.0</angle>
    </robndbox>
  </object>
</annotation>
