<annotation verified="no">
  <folder>20210115</folder>
  <filename>0_80_80_0_02246</filename>
  <path>D:\drone_hot\images_data\day\80m\-80\20210115\0_80_80_0_02246.jpg</path>
  <source>
    <database>Unknown</database>
  </source>
  <size>
    <width>640</width>
    <height>512</height>
    <depth>1</depth>
  </size>
  <segmented>0</segmented>
  <object>
    <type>robndbox</type>
    <name>Person</name>
    <pose>Unspecified</pose>
    <truncated>0</truncated>
    <difficult>0</difficult>
    <robndbox>
      <cx>634.3313</cx>
      <cy>41.3735</cy>
      <w>10.0</w>
      <h>18.0</h>
      <angle>0.0</angle>
    </robndbox>
  </object>
  <object>
    <type>robndbox</type>
    <name>Person</name>
    <pose>Unspecified</pose>
    <truncated>0</truncated>
    <difficult>0</difficult>
    <robndbox>
      <cx>494.8313</cx>
      <cy>198.3735</cy>
      <w>15.0</w>
      <h>18.0</h>
      <angle>0.0</angle>
    </robndbox>
  </object>
  <object>
    <type>robndbox</type>
    <name>Person</name>
    <pose>Unspecified</pose>
    <truncated>0</truncated>
    <difficult>0</difficult>
    <robndbox>
      <cx>475.3313</cx>
      <cy>238.3735</cy>
      <w>14.0</w>
      <h>18.0</h>
      <angle>0.0</angle>
    </robndbox>
  </object>
  <object>
    <type>robndbox</type>
    <name>Person</name>
    <pose>Unspecified</pose>
    <truncated>0</truncated>
    <difficult>0</difficult>
    <robndbox>
      <cx>422.8313</cx>
      <cy>227.3735</cy>
      <w>11.0</w>
      <h>20.0</h>
      <angle>0.0</angle>
    </robndbox>
  </object>
  <object>
    <type>robndbox</type>
    <name>Person</name>
    <pose>Unspecified</pose>
    <truncated>0</truncated>
    <difficult>0</difficult>
    <robndbox>
      <cx>371.3313</cx>
      <cy>204.8735</cy>
      <w>20.0</w>
      <h>15.0</h>
      <angle>0.0</angle>
    </robndbox>
  </object>
  <object>
    <type>robndbox</type>
    <name>Person</name>
    <pose>Unspecified</pose>
    <truncated>0</truncated>
    <difficult>0</difficult>
    <robndbox>
      <cx>396.8313</cx>
      <cy>238.8735</cy>
      <w>19.0</w>
      <h>19.0</h>
      <angle>0.0</angle>
    </robndbox>
  </object>
  <object>
    <type>robndbox</type>
    <name>Person</name>
    <pose>Unspecified</pose>
    <truncated>0</truncated>
    <difficult>0</difficult>
    <robndbox>
      <cx>376.3313</cx>
      <cy>248.3735</cy>
      <w>18.0</w>
      <h>20.0</h>
      <angle>0.0</angle>
    </robndbox>
  </object>
  <object>
    <type>robndbox</type>
    <name>Person</name>
    <pose>Unspecified</pose>
    <truncated>0</truncated>
    <difficult>0</difficult>
    <robndbox>
      <cx>374.0637</cx>
      <cy>305.6903</cy>
      <w>11.4382</w>
      <h>12.6023</h>
      <angle>0.069508</angle>
    </robndbox>
  </object>
  <object>
    <type>robndbox</type>
    <name>Person</name>
    <pose>Unspecified</pose>
    <truncated>0</truncated>
    <difficult>0</difficult>
    <robndbox>
      <cx>446.9013</cx>
      <cy>284.5834</cy>
      <w>13.2953</w>
      <h>20.6475</h>
      <angle>0.288975</angle>
    </robndbox>
  </object>
  <object>
    <type>robndbox</type>
    <name>Person</name>
    <pose>Unspecified</pose>
    <truncated>0</truncated>
    <difficult>0</difficult>
    <robndbox>
      <cx>465.2692</cx>
      <cy>309.4622</cy>
      <w>17.1879</w>
      <h>18.0198</h>
      <angle>0.558342</angle>
    </robndbox>
  </object>
</annotation>
