<annotation verified="no">
  <folder>20210119</folder>
  <filename>1_100_70_0_06353</filename>
  <path>D:\drone_hot\images_data\night\100m\-70\20210119\1_100_70_0_06353.jpg</path>
  <source>
    <database>Unknown</database>
  </source>
  <size>
    <width>640</width>
    <height>512</height>
    <depth>1</depth>
  </size>
  <segmented>0</segmented>
  <object>
    <type>robndbox</type>
    <name>Car</name>
    <pose>Unspecified</pose>
    <truncated>0</truncated>
    <difficult>0</difficult>
    <robndbox>
      <cx>47.717</cx>
      <cy>36.8344</cy>
      <w>33.9223</w>
      <h>65.3668</h>
      <angle>0.502937</angle>
    </robndbox>
  </object>
  <object>
    <type>robndbox</type>
    <name>Car</name>
    <pose>Unspecified</pose>
    <truncated>0</truncated>
    <difficult>0</difficult>
    <robndbox>
      <cx>93.8192</cx>
      <cy>58.7666</cy>
      <w>39.4298</w>
      <h>75.5778</h>
      <angle>0.502937</angle>
    </robndbox>
  </object>
  <object>
    <type>robndbox</type>
    <name>Person</name>
    <pose>Unspecified</pose>
    <truncated>0</truncated>
    <difficult>0</difficult>
    <robndbox>
      <cx>291.3313</cx>
      <cy>119.3735</cy>
      <w>16.0</w>
      <h>20.0</h>
      <angle>3.078519</angle>
    </robndbox>
  </object>
  <object>
    <type>robndbox</type>
    <name>Person</name>
    <pose>Unspecified</pose>
    <truncated>0</truncated>
    <difficult>0</difficult>
    <robndbox>
      <cx>322.8313</cx>
      <cy>119.8735</cy>
      <w>17.0</w>
      <h>19.0</h>
      <angle>0.0</angle>
    </robndbox>
  </object>
  <object>
    <type>robndbox</type>
    <name>Car</name>
    <pose>Unspecified</pose>
    <truncated>0</truncated>
    <difficult>0</difficult>
    <robndbox>
      <cx>395.3313</cx>
      <cy>204.3735</cy>
      <w>38.6197</w>
      <h>78.1826</h>
      <angle>0.473072</angle>
    </robndbox>
  </object>
  <object>
    <type>robndbox</type>
    <name>Car</name>
    <pose>Unspecified</pose>
    <truncated>0</truncated>
    <difficult>0</difficult>
    <robndbox>
      <cx>465.4066</cx>
      <cy>215.5545</cy>
      <w>35.4752</w>
      <h>75.2023</h>
      <angle>0.519958</angle>
    </robndbox>
  </object>
  <object>
    <type>robndbox</type>
    <name>Car</name>
    <pose>Unspecified</pose>
    <truncated>0</truncated>
    <difficult>0</difficult>
    <robndbox>
      <cx>517.6269</cx>
      <cy>257.6661</cy>
      <w>37.9399</w>
      <h>83.0714</h>
      <angle>0.490363</angle>
    </robndbox>
  </object>
  <object>
    <type>robndbox</type>
    <name>Car</name>
    <pose>Unspecified</pose>
    <truncated>0</truncated>
    <difficult>0</difficult>
    <robndbox>
      <cx>564.8313</cx>
      <cy>278.8735</cy>
      <w>35.3514</w>
      <h>74.0289</h>
      <angle>0.322644</angle>
    </robndbox>
  </object>
  <object>
    <type>robndbox</type>
    <name>Car</name>
    <pose>Unspecified</pose>
    <truncated>0</truncated>
    <difficult>0</difficult>
    <robndbox>
      <cx>610.558</cx>
      <cy>298.8735</cy>
      <w>35.3514</w>
      <h>74.0289</h>
      <angle>0.320678</angle>
    </robndbox>
  </object>
  <object>
    <type>robndbox</type>
    <name>Car</name>
    <pose>Unspecified</pose>
    <truncated>0</truncated>
    <difficult>0</difficult>
    <robndbox>
      <cx>569.8313</cx>
      <cy>195.8735</cy>
      <w>82.3731</w>
      <h>43.1819</h>
      <angle>0.472086</angle>
    </robndbox>
  </object>
</annotation>
