<annotation verified="no">
  <folder>20210115</folder>
  <filename>1_120_40_0_02851</filename>
  <path>D:\js\images_data\night\120m\-40\20210115\1_120_40_0_02851.jpg</path>
  <source>
    <database>Unknown</database>
  </source>
  <size>
    <width>640</width>
    <height>512</height>
    <depth>1</depth>
  </size>
  <segmented>0</segmented>
  <object>
    <type>robndbox</type>
    <name>Person</name>
    <pose>Unspecified</pose>
    <truncated>0</truncated>
    <difficult>0</difficult>
    <robndbox>
      <cx>132.5</cx>
      <cy>74.5</cy>
      <w>7.0</w>
      <h>13.0</h>
      <angle>0.0</angle>
    </robndbox>
  </object>
  <object>
    <type>robndbox</type>
    <name>Person</name>
    <pose>Unspecified</pose>
    <truncated>0</truncated>
    <difficult>0</difficult>
    <robndbox>
      <cx>159.5</cx>
      <cy>95.5</cy>
      <w>7.0</w>
      <h>13.0</h>
      <angle>0.0</angle>
    </robndbox>
  </object>
  <object>
    <type>robndbox</type>
    <name>Person</name>
    <pose>Unspecified</pose>
    <truncated>0</truncated>
    <difficult>0</difficult>
    <robndbox>
      <cx>277.5</cx>
      <cy>87.0</cy>
      <w>9.0</w>
      <h>14.0</h>
      <angle>0.0</angle>
    </robndbox>
  </object>
  <object>
    <type>robndbox</type>
    <name>Person</name>
    <pose>Unspecified</pose>
    <truncated>0</truncated>
    <difficult>0</difficult>
    <robndbox>
      <cx>311.0</cx>
      <cy>81.5</cy>
      <w>6.0</w>
      <h>13.0</h>
      <angle>0.0</angle>
    </robndbox>
  </object>
  <object>
    <type>robndbox</type>
    <name>Person</name>
    <pose>Unspecified</pose>
    <truncated>0</truncated>
    <difficult>0</difficult>
    <robndbox>
      <cx>304.5</cx>
      <cy>87.5</cy>
      <w>7.0</w>
      <h>15.0</h>
      <angle>0.0</angle>
    </robndbox>
  </object>
  <object>
    <type>robndbox</type>
    <name>Person</name>
    <pose>Unspecified</pose>
    <truncated>0</truncated>
    <difficult>0</difficult>
    <robndbox>
      <cx>296.0</cx>
      <cy>83.0</cy>
      <w>8.0</w>
      <h>14.0</h>
      <angle>0.0</angle>
    </robndbox>
  </object>
  <object>
    <type>robndbox</type>
    <name>Person</name>
    <pose>Unspecified</pose>
    <truncated>0</truncated>
    <difficult>0</difficult>
    <robndbox>
      <cx>288.0</cx>
      <cy>91.0</cy>
      <w>8.0</w>
      <h>14.0</h>
      <angle>0.0</angle>
    </robndbox>
  </object>
  <object>
    <type>robndbox</type>
    <name>Person</name>
    <pose>Unspecified</pose>
    <truncated>0</truncated>
    <difficult>0</difficult>
    <robndbox>
      <cx>301.0</cx>
      <cy>101.0</cy>
      <w>6.0</w>
      <h>12.0</h>
      <angle>0.0</angle>
    </robndbox>
  </object>
  <object>
    <type>robndbox</type>
    <name>Person</name>
    <pose>Unspecified</pose>
    <truncated>0</truncated>
    <difficult>0</difficult>
    <robndbox>
      <cx>509.5</cx>
      <cy>169.0</cy>
      <w>8.0856</w>
      <h>14.6841</h>
      <angle>0.200446</angle>
    </robndbox>
  </object>
  <object>
    <type>robndbox</type>
    <name>Person</name>
    <pose>Unspecified</pose>
    <truncated>0</truncated>
    <difficult>0</difficult>
    <robndbox>
      <cx>547.0</cx>
      <cy>178.0</cy>
      <w>8.0</w>
      <h>14.0</h>
      <angle>0.0</angle>
    </robndbox>
  </object>
  <object>
    <type>robndbox</type>
    <name>Person</name>
    <pose>Unspecified</pose>
    <truncated>0</truncated>
    <difficult>0</difficult>
    <robndbox>
      <cx>58.5</cx>
      <cy>360.5</cy>
      <w>7.0</w>
      <h>9.0</h>
      <angle>0.0</angle>
    </robndbox>
  </object>
  <object>
    <type>robndbox</type>
    <name>Person</name>
    <pose>Unspecified</pose>
    <truncated>0</truncated>
    <difficult>0</difficult>
    <robndbox>
      <cx>55.5</cx>
      <cy>370.5</cy>
      <w>9.0</w>
      <h>13.0</h>
      <angle>0.0</angle>
    </robndbox>
  </object>
  <object>
    <type>robndbox</type>
    <name>Person</name>
    <pose>Unspecified</pose>
    <truncated>0</truncated>
    <difficult>0</difficult>
    <robndbox>
      <cx>66.5</cx>
      <cy>367.0</cy>
      <w>7.0</w>
      <h>12.0</h>
      <angle>0.0</angle>
    </robndbox>
  </object>
  <object>
    <type>robndbox</type>
    <name>Person</name>
    <pose>Unspecified</pose>
    <truncated>0</truncated>
    <difficult>0</difficult>
    <robndbox>
      <cx>75.5</cx>
      <cy>387.5</cy>
      <w>7.0</w>
      <h>15.0</h>
      <angle>0.0</angle>
    </robndbox>
  </object>
  <object>
    <type>robndbox</type>
    <name>Person</name>
    <pose>Unspecified</pose>
    <truncated>0</truncated>
    <difficult>0</difficult>
    <robndbox>
      <cx>82.0</cx>
      <cy>468.5</cy>
      <w>6.0</w>
      <h>13.0</h>
      <angle>0.0</angle>
    </robndbox>
  </object>
  <object>
    <type>robndbox</type>
    <name>Person</name>
    <pose>Unspecified</pose>
    <truncated>0</truncated>
    <difficult>0</difficult>
    <robndbox>
      <cx>82.5</cx>
      <cy>484.0</cy>
      <w>7.0</w>
      <h>16.0</h>
      <angle>0.0</angle>
    </robndbox>
  </object>
  <object>
    <type>robndbox</type>
    <name>Person</name>
    <pose>Unspecified</pose>
    <truncated>0</truncated>
    <difficult>0</difficult>
    <robndbox>
      <cx>94.5</cx>
      <cy>473.0</cy>
      <w>7.0</w>
      <h>14.0</h>
      <angle>0.0</angle>
    </robndbox>
  </object>
  <object>
    <type>robndbox</type>
    <name>Person</name>
    <pose>Unspecified</pose>
    <truncated>0</truncated>
    <difficult>0</difficult>
    <robndbox>
      <cx>102.5</cx>
      <cy>467.0</cy>
      <w>7.0</w>
      <h>14.0</h>
      <angle>0.0</angle>
    </robndbox>
  </object>
  <object>
    <type>robndbox</type>
    <name>Person</name>
    <pose>Unspecified</pose>
    <truncated>0</truncated>
    <difficult>0</difficult>
    <robndbox>
      <cx>126.0</cx>
      <cy>477.5</cy>
      <w>8.0</w>
      <h>15.0</h>
      <angle>0.0</angle>
    </robndbox>
  </object>
  <object>
    <type>robndbox</type>
    <name>Person</name>
    <pose>Unspecified</pose>
    <truncated>0</truncated>
    <difficult>0</difficult>
    <robndbox>
      <cx>109.5</cx>
      <cy>488.0</cy>
      <w>7.0</w>
      <h>16.0</h>
      <angle>0.0</angle>
    </robndbox>
  </object>
  <object>
    <type>robndbox</type>
    <name>Person</name>
    <pose>Unspecified</pose>
    <truncated>0</truncated>
    <difficult>0</difficult>
    <robndbox>
      <cx>96.0938</cx>
      <cy>504.5</cy>
      <w>12.1875</w>
      <h>15.0</h>
      <angle>0.0</angle>
    </robndbox>
  </object>
  <object>
    <type>robndbox</type>
    <name>Person</name>
    <pose>Unspecified</pose>
    <truncated>0</truncated>
    <difficult>0</difficult>
    <robndbox>
      <cx>138.0</cx>
      <cy>480.5</cy>
      <w>6.0</w>
      <h>9.0</h>
      <angle>0.0</angle>
    </robndbox>
  </object>
  <object>
    <type>robndbox</type>
    <name>Person</name>
    <pose>Unspecified</pose>
    <truncated>0</truncated>
    <difficult>0</difficult>
    <robndbox>
      <cx>135.5</cx>
      <cy>471.0</cy>
      <w>4.8414</w>
      <h>11.5569</h>
      <angle>2.466852</angle>
    </robndbox>
  </object>
</annotation>
