<annotation verified="no">
  <folder>20210120</folder>
  <filename>1_130_50_0_07192</filename>
  <path>D:\js\images_data\night\130m\-50\20210120\1_130_50_0_07192.jpg</path>
  <source>
    <database>Unknown</database>
  </source>
  <size>
    <width>640</width>
    <height>512</height>
    <depth>1</depth>
  </size>
  <segmented>0</segmented>
  <object>
    <type>robndbox</type>
    <name>Car</name>
    <pose>Unspecified</pose>
    <truncated>0</truncated>
    <difficult>0</difficult>
    <robndbox>
      <cx>605.3883</cx>
      <cy>149.065</cy>
      <w>20.5904</w>
      <h>38.757</h>
      <angle>2.625362</angle>
    </robndbox>
  </object>
  <object>
    <type>robndbox</type>
    <name>Car</name>
    <pose>Unspecified</pose>
    <truncated>0</truncated>
    <difficult>0</difficult>
    <robndbox>
      <cx>406.5</cx>
      <cy>44.5</cy>
      <w>55.0</w>
      <h>23.0</h>
      <angle>0.0</angle>
    </robndbox>
  </object>
  <object>
    <type>robndbox</type>
    <name>Person</name>
    <pose>Unspecified</pose>
    <truncated>0</truncated>
    <difficult>0</difficult>
    <robndbox>
      <cx>195.5</cx>
      <cy>183.5</cy>
      <w>9.0</w>
      <h>19.0</h>
      <angle>0.0</angle>
    </robndbox>
  </object>
  <object>
    <type>robndbox</type>
    <name>Person</name>
    <pose>Unspecified</pose>
    <truncated>0</truncated>
    <difficult>0</difficult>
    <robndbox>
      <cx>203.5</cx>
      <cy>176.0</cy>
      <w>11.0</w>
      <h>24.0</h>
      <angle>0.0</angle>
    </robndbox>
  </object>
  <object>
    <type>robndbox</type>
    <name>Person</name>
    <pose>Unspecified</pose>
    <truncated>0</truncated>
    <difficult>0</difficult>
    <robndbox>
      <cx>214.5</cx>
      <cy>184.0</cy>
      <w>11.0</w>
      <h>20.0</h>
      <angle>0.0</angle>
    </robndbox>
  </object>
  <object>
    <type>robndbox</type>
    <name>Car</name>
    <pose>Unspecified</pose>
    <truncated>0</truncated>
    <difficult>0</difficult>
    <robndbox>
      <cx>565.0</cx>
      <cy>209.6842</cy>
      <w>84.0</w>
      <h>56.0</h>
      <angle>0.0</angle>
    </robndbox>
  </object>
</annotation>
