<annotation verified="no">
  <folder>20210116</folder>
  <filename>1_60_70_0_04213</filename>
  <path>D:\drone_hot\images_data\night\60m\-70\20210116\1_60_70_0_04213.jpg</path>
  <source>
    <database>Unknown</database>
  </source>
  <size>
    <width>640</width>
    <height>512</height>
    <depth>1</depth>
  </size>
  <segmented>0</segmented>
  <object>
    <type>robndbox</type>
    <name>Car</name>
    <pose>Unspecified</pose>
    <truncated>0</truncated>
    <difficult>0</difficult>
    <robndbox>
      <cx>192.8313</cx>
      <cy>497.0</cy>
      <w>91.0</w>
      <h>28.0</h>
      <angle>0.0</angle>
    </robndbox>
  </object>
  <object>
    <type>robndbox</type>
    <name>Car</name>
    <pose>Unspecified</pose>
    <truncated>0</truncated>
    <difficult>0</difficult>
    <robndbox>
      <cx>205.3313</cx>
      <cy>418.8735</cy>
      <w>96.1314</w>
      <h>43.1713</h>
      <angle>0.260066</angle>
    </robndbox>
  </object>
  <object>
    <type>robndbox</type>
    <name>Car</name>
    <pose>Unspecified</pose>
    <truncated>0</truncated>
    <difficult>0</difficult>
    <robndbox>
      <cx>212.3313</cx>
      <cy>368.8735</cy>
      <w>96.1314</w>
      <h>43.1713</h>
      <angle>0.260066</angle>
    </robndbox>
  </object>
  <object>
    <type>robndbox</type>
    <name>Car</name>
    <pose>Unspecified</pose>
    <truncated>0</truncated>
    <difficult>0</difficult>
    <robndbox>
      <cx>224.3147</cx>
      <cy>325.4216</cy>
      <w>95.9254</w>
      <h>42.2906</h>
      <angle>0.192996</angle>
    </robndbox>
  </object>
  <object>
    <type>robndbox</type>
    <name>Car</name>
    <pose>Unspecified</pose>
    <truncated>0</truncated>
    <difficult>0</difficult>
    <robndbox>
      <cx>232.3147</cx>
      <cy>280.9216</cy>
      <w>95.7336</w>
      <h>41.3091</h>
      <angle>0.192996</angle>
    </robndbox>
  </object>
  <object>
    <type>robndbox</type>
    <name>Car</name>
    <pose>Unspecified</pose>
    <truncated>0</truncated>
    <difficult>0</difficult>
    <robndbox>
      <cx>245.3147</cx>
      <cy>238.9216</cy>
      <w>95.7336</w>
      <h>41.3091</h>
      <angle>0.192996</angle>
    </robndbox>
  </object>
  <object>
    <type>robndbox</type>
    <name>Car</name>
    <pose>Unspecified</pose>
    <truncated>0</truncated>
    <difficult>0</difficult>
    <robndbox>
      <cx>256.3147</cx>
      <cy>191.9216</cy>
      <w>95.7336</w>
      <h>41.3091</h>
      <angle>0.250295</angle>
    </robndbox>
  </object>
  <object>
    <type>robndbox</type>
    <name>Car</name>
    <pose>Unspecified</pose>
    <truncated>0</truncated>
    <difficult>0</difficult>
    <robndbox>
      <cx>293.6663</cx>
      <cy>110.1198</cy>
      <w>95.148</w>
      <h>43.9703</h>
      <angle>0.27943</angle>
    </robndbox>
  </object>
  <object>
    <type>robndbox</type>
    <name>Car</name>
    <pose>Unspecified</pose>
    <truncated>0</truncated>
    <difficult>0</difficult>
    <robndbox>
      <cx>308.1663</cx>
      <cy>65.1198</cy>
      <w>95.006</w>
      <h>39.8497</h>
      <angle>0.27943</angle>
    </robndbox>
  </object>
  <object>
    <type>robndbox</type>
    <name>Car</name>
    <pose>Unspecified</pose>
    <truncated>0</truncated>
    <difficult>0</difficult>
    <robndbox>
      <cx>486.3313</cx>
      <cy>42.8735</cy>
      <w>95.6808</w>
      <h>41.4992</h>
      <angle>3.052262</angle>
    </robndbox>
  </object>
  <object>
    <type>robndbox</type>
    <name>Car</name>
    <pose>Unspecified</pose>
    <truncated>0</truncated>
    <difficult>0</difficult>
    <robndbox>
      <cx>319.1663</cx>
      <cy>27.6867</cy>
      <w>84.7971</w>
      <h>33.2765</h>
      <angle>0.27943</angle>
    </robndbox>
  </object>
</annotation>
