<annotation verified="no">
  <folder>20201217</folder>
  <filename>1_60_50_0_00324</filename>
  <path>D:\drone_hot\images_data\night\60m\-50\20201217\1_60_50_0_00324.jpg</path>
  <source>
    <database>Unknown</database>
  </source>
  <size>
    <width>640</width>
    <height>512</height>
    <depth>1</depth>
  </size>
  <segmented>0</segmented>
  <object>
    <type>robndbox</type>
    <name>Person</name>
    <pose>Unspecified</pose>
    <truncated>0</truncated>
    <difficult>0</difficult>
    <robndbox>
      <cx>39.5181</cx>
      <cy>5.1867</cy>
      <w>10.3735</w>
      <h>10.3735</h>
      <angle>0.0</angle>
    </robndbox>
  </object>
  <object>
    <type>robndbox</type>
    <name>Person</name>
    <pose>Unspecified</pose>
    <truncated>0</truncated>
    <difficult>0</difficult>
    <robndbox>
      <cx>287.8313</cx>
      <cy>87.3735</cy>
      <w>15.0</w>
      <h>26.0</h>
      <angle>0.0</angle>
    </robndbox>
  </object>
  <object>
    <type>robndbox</type>
    <name>Person</name>
    <pose>Unspecified</pose>
    <truncated>0</truncated>
    <difficult>0</difficult>
    <robndbox>
      <cx>250.3313</cx>
      <cy>132.3735</cy>
      <w>14.0</w>
      <h>26.0</h>
      <angle>3.095115</angle>
    </robndbox>
  </object>
  <object>
    <type>robndbox</type>
    <name>Person</name>
    <pose>Unspecified</pose>
    <truncated>0</truncated>
    <difficult>0</difficult>
    <robndbox>
      <cx>310.8313</cx>
      <cy>179.3735</cy>
      <w>13.0</w>
      <h>34.0</h>
      <angle>0.0</angle>
    </robndbox>
  </object>
  <object>
    <type>robndbox</type>
    <name>Person</name>
    <pose>Unspecified</pose>
    <truncated>0</truncated>
    <difficult>0</difficult>
    <robndbox>
      <cx>203.8313</cx>
      <cy>327.8735</cy>
      <w>13.0</w>
      <h>27.0</h>
      <angle>0.0</angle>
    </robndbox>
  </object>
  <object>
    <type>robndbox</type>
    <name>Person</name>
    <pose>Unspecified</pose>
    <truncated>0</truncated>
    <difficult>0</difficult>
    <robndbox>
      <cx>190.8313</cx>
      <cy>331.8735</cy>
      <w>13.0</w>
      <h>31.0</h>
      <angle>0.0</angle>
    </robndbox>
  </object>
  <object>
    <type>robndbox</type>
    <name>Person</name>
    <pose>Unspecified</pose>
    <truncated>0</truncated>
    <difficult>0</difficult>
    <robndbox>
      <cx>462.3313</cx>
      <cy>214.8735</cy>
      <w>14.0</w>
      <h>29.0</h>
      <angle>0.0</angle>
    </robndbox>
  </object>
</annotation>
