<annotation verified="no">
  <folder>20210120</folder>
  <filename>1_60_90_0_07553</filename>
  <path>D:\drone_hot\images_data\night\60m\-90\20210120\1_60_90_0_07553.jpg</path>
  <source>
    <database>Unknown</database>
  </source>
  <size>
    <width>640</width>
    <height>512</height>
    <depth>1</depth>
  </size>
  <segmented>0</segmented>
  <object>
    <type>robndbox</type>
    <name>Bicycle</name>
    <pose>Unspecified</pose>
    <truncated>0</truncated>
    <difficult>0</difficult>
    <robndbox>
      <cx>96.8107</cx>
      <cy>22.2563</cy>
      <w>42.8847</w>
      <h>16.8972</h>
      <angle>2.231112</angle>
    </robndbox>
  </object>
  <object>
    <type>robndbox</type>
    <name>Bicycle</name>
    <pose>Unspecified</pose>
    <truncated>0</truncated>
    <difficult>0</difficult>
    <robndbox>
      <cx>118.8107</cx>
      <cy>36.1867</cy>
      <w>47.2123</w>
      <h>27.8549</h>
      <angle>2.188569</angle>
    </robndbox>
  </object>
  <object>
    <type>robndbox</type>
    <name>Bicycle</name>
    <pose>Unspecified</pose>
    <truncated>0</truncated>
    <difficult>0</difficult>
    <robndbox>
      <cx>143.731</cx>
      <cy>49.6251</cy>
      <w>60.1182</w>
      <h>31.9227</h>
      <angle>2.188569</angle>
    </robndbox>
  </object>
  <object>
    <type>robndbox</type>
    <name>Bicycle</name>
    <pose>Unspecified</pose>
    <truncated>0</truncated>
    <difficult>0</difficult>
    <robndbox>
      <cx>159.5719</cx>
      <cy>73.7074</cy>
      <w>59.1264</w>
      <h>26.8881</h>
      <angle>1.89835</angle>
    </robndbox>
  </object>
  <object>
    <type>robndbox</type>
    <name>Bicycle</name>
    <pose>Unspecified</pose>
    <truncated>0</truncated>
    <difficult>0</difficult>
    <robndbox>
      <cx>179.8661</cx>
      <cy>67.5339</cy>
      <w>55.1209</w>
      <h>17.6884</h>
      <angle>1.796046</angle>
    </robndbox>
  </object>
  <object>
    <type>robndbox</type>
    <name>Bicycle</name>
    <pose>Unspecified</pose>
    <truncated>0</truncated>
    <difficult>0</difficult>
    <robndbox>
      <cx>292.8251</cx>
      <cy>41.8617</cy>
      <w>32.849</w>
      <h>60.024</h>
      <angle>0.599481</angle>
    </robndbox>
  </object>
  <object>
    <type>robndbox</type>
    <name>Bicycle</name>
    <pose>Unspecified</pose>
    <truncated>0</truncated>
    <difficult>0</difficult>
    <robndbox>
      <cx>268.3313</cx>
      <cy>26.0</cy>
      <w>40.0</w>
      <h>52.0</h>
      <angle>0.0</angle>
    </robndbox>
  </object>
  <object>
    <type>robndbox</type>
    <name>Bicycle</name>
    <pose>Unspecified</pose>
    <truncated>0</truncated>
    <difficult>0</difficult>
    <robndbox>
      <cx>199.6552</cx>
      <cy>74.5104</cy>
      <w>52.8468</w>
      <h>21.481</h>
      <angle>2.121561</angle>
    </robndbox>
  </object>
  <object>
    <type>robndbox</type>
    <name>Bicycle</name>
    <pose>Unspecified</pose>
    <truncated>0</truncated>
    <difficult>0</difficult>
    <robndbox>
      <cx>225.8313</cx>
      <cy>81.8735</cy>
      <w>63.8957</w>
      <h>23.9861</h>
      <angle>2.121561</angle>
    </robndbox>
  </object>
  <object>
    <type>robndbox</type>
    <name>Bicycle</name>
    <pose>Unspecified</pose>
    <truncated>0</truncated>
    <difficult>0</difficult>
    <robndbox>
      <cx>255.8313</cx>
      <cy>95.3735</cy>
      <w>70.9073</w>
      <h>25.9452</h>
      <angle>2.121561</angle>
    </robndbox>
  </object>
  <object>
    <type>robndbox</type>
    <name>Bicycle</name>
    <pose>Unspecified</pose>
    <truncated>0</truncated>
    <difficult>0</difficult>
    <robndbox>
      <cx>272.8313</cx>
      <cy>117.8735</cy>
      <w>64.5533</w>
      <h>26.737</h>
      <angle>2.121561</angle>
    </robndbox>
  </object>
  <object>
    <type>robndbox</type>
    <name>Bicycle</name>
    <pose>Unspecified</pose>
    <truncated>0</truncated>
    <difficult>0</difficult>
    <robndbox>
      <cx>296.8313</cx>
      <cy>135.8735</cy>
      <w>75.1679</w>
      <h>28.5619</h>
      <angle>2.121561</angle>
    </robndbox>
  </object>
  <object>
    <type>robndbox</type>
    <name>Bicycle</name>
    <pose>Unspecified</pose>
    <truncated>0</truncated>
    <difficult>0</difficult>
    <robndbox>
      <cx>363.8548</cx>
      <cy>25.6859</cy>
      <w>40.1353</w>
      <h>18.3703</h>
      <angle>1.921689</angle>
    </robndbox>
  </object>
  <object>
    <type>robndbox</type>
    <name>Bicycle</name>
    <pose>Unspecified</pose>
    <truncated>0</truncated>
    <difficult>0</difficult>
    <robndbox>
      <cx>385.7293</cx>
      <cy>42.0286</cy>
      <w>54.5154</w>
      <h>27.6263</h>
      <angle>1.921689</angle>
    </robndbox>
  </object>
  <object>
    <type>robndbox</type>
    <name>Bicycle</name>
    <pose>Unspecified</pose>
    <truncated>0</truncated>
    <difficult>0</difficult>
    <robndbox>
      <cx>434.6751</cx>
      <cy>68.495</cy>
      <w>64.9896</w>
      <h>23.527</h>
      <angle>2.293345</angle>
    </robndbox>
  </object>
  <object>
    <type>robndbox</type>
    <name>Bicycle</name>
    <pose>Unspecified</pose>
    <truncated>0</truncated>
    <difficult>0</difficult>
    <robndbox>
      <cx>513.4008</cx>
      <cy>93.0775</cy>
      <w>59.7298</w>
      <h>31.3831</h>
      <angle>2.187245</angle>
    </robndbox>
  </object>
  <object>
    <type>robndbox</type>
    <name>Bicycle</name>
    <pose>Unspecified</pose>
    <truncated>0</truncated>
    <difficult>0</difficult>
    <robndbox>
      <cx>532.0975</cx>
      <cy>102.0056</cy>
      <w>61.8002</w>
      <h>24.7531</h>
      <angle>2.187245</angle>
    </robndbox>
  </object>
  <object>
    <type>robndbox</type>
    <name>Bicycle</name>
    <pose>Unspecified</pose>
    <truncated>0</truncated>
    <difficult>0</difficult>
    <robndbox>
      <cx>547.5829</cx>
      <cy>122.9074</cy>
      <w>58.3852</w>
      <h>21.4347</h>
      <angle>2.113374</angle>
    </robndbox>
  </object>
  <object>
    <type>robndbox</type>
    <name>Bicycle</name>
    <pose>Unspecified</pose>
    <truncated>0</truncated>
    <difficult>0</difficult>
    <robndbox>
      <cx>382.1501</cx>
      <cy>116.6676</cy>
      <w>58.2367</w>
      <h>27.6582</h>
      <angle>2.195688</angle>
    </robndbox>
  </object>
  <object>
    <type>robndbox</type>
    <name>Bicycle</name>
    <pose>Unspecified</pose>
    <truncated>0</truncated>
    <difficult>0</difficult>
    <robndbox>
      <cx>422.4327</cx>
      <cy>131.9581</cy>
      <w>64.0857</w>
      <h>38.5876</h>
      <angle>2.115286</angle>
    </robndbox>
  </object>
  <object>
    <type>robndbox</type>
    <name>Bicycle</name>
    <pose>Unspecified</pose>
    <truncated>0</truncated>
    <difficult>0</difficult>
    <robndbox>
      <cx>351.2948</cx>
      <cy>187.1858</cy>
      <w>64.6181</w>
      <h>36.8768</h>
      <angle>2.115286</angle>
    </robndbox>
  </object>
  <object>
    <type>robndbox</type>
    <name>Bicycle</name>
    <pose>Unspecified</pose>
    <truncated>0</truncated>
    <difficult>0</difficult>
    <robndbox>
      <cx>378.7948</cx>
      <cy>198.1858</cy>
      <w>55.9074</w>
      <h>28.0948</h>
      <angle>2.115286</angle>
    </robndbox>
  </object>
  <object>
    <type>robndbox</type>
    <name>Bicycle</name>
    <pose>Unspecified</pose>
    <truncated>0</truncated>
    <difficult>0</difficult>
    <robndbox>
      <cx>409.7948</cx>
      <cy>207.6858</cy>
      <w>53.7023</w>
      <h>22.0834</h>
      <angle>2.115286</angle>
    </robndbox>
  </object>
  <object>
    <type>robndbox</type>
    <name>Bicycle</name>
    <pose>Unspecified</pose>
    <truncated>0</truncated>
    <difficult>0</difficult>
    <robndbox>
      <cx>435.9912</cx>
      <cy>213.4596</cy>
      <w>60.8368</w>
      <h>25.5169</h>
      <angle>1.765656</angle>
    </robndbox>
  </object>
  <object>
    <type>robndbox</type>
    <name>Bicycle</name>
    <pose>Unspecified</pose>
    <truncated>0</truncated>
    <difficult>0</difficult>
    <robndbox>
      <cx>324.8313</cx>
      <cy>244.8735</cy>
      <w>62.3022</w>
      <h>27.1373</h>
      <angle>2.557348</angle>
    </robndbox>
  </object>
  <object>
    <type>robndbox</type>
    <name>Bicycle</name>
    <pose>Unspecified</pose>
    <truncated>0</truncated>
    <difficult>0</difficult>
    <robndbox>
      <cx>384.4549</cx>
      <cy>269.8142</cy>
      <w>67.0907</w>
      <h>30.134</h>
      <angle>2.096971</angle>
    </robndbox>
  </object>
  <object>
    <type>robndbox</type>
    <name>Bicycle</name>
    <pose>Unspecified</pose>
    <truncated>0</truncated>
    <difficult>0</difficult>
    <robndbox>
      <cx>432.1259</cx>
      <cy>296.2894</cy>
      <w>67.033</w>
      <h>30.2207</h>
      <angle>2.140129</angle>
    </robndbox>
  </object>
  <object>
    <type>robndbox</type>
    <name>Bicycle</name>
    <pose>Unspecified</pose>
    <truncated>0</truncated>
    <difficult>0</difficult>
    <robndbox>
      <cx>319.3313</cx>
      <cy>306.3735</cy>
      <w>56.1008</w>
      <h>24.5092</h>
      <angle>1.828546</angle>
    </robndbox>
  </object>
  <object>
    <type>robndbox</type>
    <name>Bicycle</name>
    <pose>Unspecified</pose>
    <truncated>0</truncated>
    <difficult>0</difficult>
    <robndbox>
      <cx>442.1541</cx>
      <cy>379.0112</cy>
      <w>61.1659</w>
      <h>19.1048</h>
      <angle>1.6798</angle>
    </robndbox>
  </object>
  <object>
    <type>robndbox</type>
    <name>Bicycle</name>
    <pose>Unspecified</pose>
    <truncated>0</truncated>
    <difficult>0</difficult>
    <robndbox>
      <cx>492.6582</cx>
      <cy>397.7072</cy>
      <w>59.2495</w>
      <h>25.7029</h>
      <angle>1.35869</angle>
    </robndbox>
  </object>
  <object>
    <type>robndbox</type>
    <name>Bicycle</name>
    <pose>Unspecified</pose>
    <truncated>0</truncated>
    <difficult>0</difficult>
    <robndbox>
      <cx>546.2672</cx>
      <cy>447.8536</cy>
      <w>67.1992</w>
      <h>27.962</h>
      <angle>0.83368</angle>
    </robndbox>
  </object>
  <object>
    <type>robndbox</type>
    <name>Bicycle</name>
    <pose>Unspecified</pose>
    <truncated>0</truncated>
    <difficult>0</difficult>
    <robndbox>
      <cx>606.8313</cx>
      <cy>490.0</cy>
      <w>37.0</w>
      <h>42.0</h>
      <angle>0.0</angle>
    </robndbox>
  </object>
</annotation>
